tuigpt/__init__.py
tuigpt/__main__.py
tuigpt/main.py
tuigpt/send.py
tuigpt/back/__init__.py
tuigpt/back/setup.py
tuigpt/back/g4f/__init__.py
tuigpt/back/g4f/models.py
tuigpt/back/g4f/typing.py
tuigpt/back/g4f/Provider/AItianhu.py
tuigpt/back/g4f/Provider/Acytoo.py
tuigpt/back/g4f/Provider/AiService.py
tuigpt/back/g4f/Provider/Aichat.py
tuigpt/back/g4f/Provider/Ails.py
tuigpt/back/g4f/Provider/Aivvm.py
tuigpt/back/g4f/Provider/Bard.py
tuigpt/back/g4f/Provider/Bing.py
tuigpt/back/g4f/Provider/ChatBase.py
tuigpt/back/g4f/Provider/ChatgptAi.py
tuigpt/back/g4f/Provider/ChatgptLogin.py
tuigpt/back/g4f/Provider/CodeLinkAva.py
tuigpt/back/g4f/Provider/DeepAi.py
tuigpt/back/g4f/Provider/DfeHub.py
tuigpt/back/g4f/Provider/EasyChat.py
tuigpt/back/g4f/Provider/Equing.py
tuigpt/back/g4f/Provider/FastGpt.py
tuigpt/back/g4f/Provider/Forefront.py
tuigpt/back/g4f/Provider/GetGpt.py
tuigpt/back/g4f/Provider/GptGo.py
tuigpt/back/g4f/Provider/H2o.py
tuigpt/back/g4f/Provider/HuggingChat.py
tuigpt/back/g4f/Provider/Liaobots.py
tuigpt/back/g4f/Provider/Lockchat.py
tuigpt/back/g4f/Provider/Opchatgpts.py
tuigpt/back/g4f/Provider/OpenAssistant.py
tuigpt/back/g4f/Provider/OpenaiChat.py
tuigpt/back/g4f/Provider/PerplexityAi.py
tuigpt/back/g4f/Provider/Raycast.py
tuigpt/back/g4f/Provider/Theb.py
tuigpt/back/g4f/Provider/V50.py
tuigpt/back/g4f/Provider/Vercel.py
tuigpt/back/g4f/Provider/Vitalentum.py
tuigpt/back/g4f/Provider/Wewordle.py
tuigpt/back/g4f/Provider/Wuguokai.py
tuigpt/back/g4f/Provider/Ylokh.py
tuigpt/back/g4f/Provider/You.py
tuigpt/back/g4f/Provider/Yqcloud.py
tuigpt/back/g4f/Provider/__init__.py
tuigpt/back/g4f/Provider/base_provider.py
tuigpt/back/g4f/Provider/retry_provider.py
tuigpt-0.3.data/data/main.py
tuigpt-0.3.dist-info/METADATA
tuigpt-0.3.dist-info/WHEEL
tuigpt-0.3.dist-info/entry_points.txt
tuigpt-0.3.dist-info/top_level.txt
tuigpt-0.3.dist-info/RECORD
